core_projeto_tech_challenge/__init__.py
core_projeto_tech_challenge/core.py
tech_challenge_fiap_gabriel-1.0.3.dist-info/METADATA
tech_challenge_fiap_gabriel-1.0.3.dist-info/WHEEL
tech_challenge_fiap_gabriel-1.0.3.dist-info/top_level.txt
tech_challenge_fiap_gabriel-1.0.3.dist-info/RECORD
