Metadata-Version: 2.4
Name: Tech_Challenge_FIAP_Gabriel
Version: 1.0.3
Summary: Teste de publicação no Pypi
Home-page: https://github.com/gabrielsiqueira97/tech-challenge-fiap
Author: Gabriel Siqueira de Lima
Author-email: gabrielsiqueira61@hotmail.com
License: MIT
Dynamic: author
Dynamic: author-email
Dynamic: description
Dynamic: description-content-type
Dynamic: home-page
Dynamic: license
Dynamic: summary
